odoo/addons/l10n_th_account_report/README.rst
odoo/addons/l10n_th_account_report/__init__.py
odoo/addons/l10n_th_account_report/__manifest__.py
odoo/addons/l10n_th_account_report/i18n/l10n_th_account_report.pot
odoo/addons/l10n_th_account_report/models/__init__.py
odoo/addons/l10n_th_account_report/models/account_vat_report.py
odoo/addons/l10n_th_account_report/readme/CONTRIBUTORS.rst
odoo/addons/l10n_th_account_report/readme/DESCRIPTION.rst
odoo/addons/l10n_th_account_report/readme/HISTORY.rst
odoo/addons/l10n_th_account_report/report_pnd/__init__.py
odoo/addons/l10n_th_account_report/report_pnd/report_pnd.py
odoo/addons/l10n_th_account_report/report_pnd/report_pnd.xml
odoo/addons/l10n_th_account_report/report_pnd/templates.xml
odoo/addons/l10n_th_account_report/report_pnd/xlsx_report_pnd.xlsx
odoo/addons/l10n_th_account_report/report_pnd/xlsx_report_pnd_txt.xlsx
odoo/addons/l10n_th_account_report/report_vat/__init__.py
odoo/addons/l10n_th_account_report/report_vat/report_vat.py
odoo/addons/l10n_th_account_report/report_vat/report_vat.xlsx
odoo/addons/l10n_th_account_report/report_vat/report_vat.xml
odoo/addons/l10n_th_account_report/report_vat/templates.xml
odoo/addons/l10n_th_account_report/security/ir.model.access.csv
odoo/addons/l10n_th_account_report/static/description/icon.png
odoo/addons/l10n_th_account_report/static/description/index.html
odoo/addons/l10n_th_account_report/tests/__init__.py
odoo/addons/l10n_th_account_report/tests/test_wt_report.py
odoo/addons/l10n_th_account_report/views/menuitems.xml
odoo12_addon_l10n_th_account_report-12.0.1.2.0.dist-info/METADATA
odoo12_addon_l10n_th_account_report-12.0.1.2.0.dist-info/RECORD
odoo12_addon_l10n_th_account_report-12.0.1.2.0.dist-info/WHEEL
odoo12_addon_l10n_th_account_report-12.0.1.2.0.dist-info/top_level.txt
